ff_inventory_api/__init__.py
ff_inventory_api/client.py
ff_inventory_api/models.py
ff_inventory_api-0.2.2.dist-info/METADATA
ff_inventory_api-0.2.2.dist-info/WHEEL
ff_inventory_api-0.2.2.dist-info/licenses/LICENSE
ff_inventory_api-0.2.2.dist-info/RECORD
