Metadata-Version: 2.4
Name: ff-inventory-api
Version: 0.2.2
Summary: Unofficial Python client for the FF-Inventory web app.
Project-URL: Homepage, https://github.com/marci4/FF-Inventory-API
Project-URL: Repository, https://github.com/marci4/FF-Inventory-API
Project-URL: Issues, https://github.com/marci4/FF-Inventory-API/issues
Author: marci4
License: MIT
License-File: LICENSE
Keywords: api,ff-inventory,firefighter,inventory,scraper
Classifier: License :: OSI Approved :: MIT License
Classifier: Operating System :: OS Independent
Classifier: Programming Language :: Python :: 3
Classifier: Programming Language :: Python :: 3 :: Only
Classifier: Programming Language :: Python :: 3.10
Requires-Python: >=3.10
Requires-Dist: beautifulsoup4>=4.12
Requires-Dist: requests>=2.28
